mimirs/__init__.py
mimirs-0.0.3.dist-info/METADATA
mimirs-0.0.3.dist-info/WHEEL
mimirs-0.0.3.dist-info/top_level.txt
mimirs-0.0.3.dist-info/RECORD
