Metadata-Version: 2.1
Name: mimirs
Version: 0.0.3
Summary: Mimir is a dict-subclass that calculates missing values through its well attribute.
Project-URL: Download, https://pypi.org/project/mimirs/#files
Classifier: Programming Language :: Python
Classifier: Programming Language :: Python :: 3
Requires-Python: >=3.11
